{"nodes": [{"id": "pages_iniciosesionadmin_iniciosesionadmin", "label": "InicioSesionAdmin Page", "file_type": "code", "source_file": "src/pages/InicioSesionAdmin.jsx", "source_location": null, "source_url": null, "captured_at": null, "author": null, "contributor": null}], "edges": [{"source": "pages_iniciosesionadmin_iniciosesionadmin", "target": "concept_admin_dual_login", "relation": "implements", "confidence": "INFERRED", "confidence_score": 0.95, "source_file": "src/pages/InicioSesionAdmin.jsx", "source_location": null, "weight": 1.0}], "hyperedges": [{"id": "admin_auth_flow", "label": "Admin Authentication Flow", "nodes": ["pages_iniciosesionadmin_iniciosesionadmin", "pages_menuadmin_menuadmin", "concept_admin_dual_login"], "relation": "implement", "confidence": "INFERRED", "confidence_score": 0.9, "source_file": "src/pages/InicioSesionAdmin.jsx"}]}